traceai_guardrails/__init__.py
traceai_guardrails/_wrap_guard_call.py
traceai_guardrails/guardrails_example.py
traceai_guardrails/version.py
traceai_guardrails-0.1.4.dist-info/METADATA
traceai_guardrails-0.1.4.dist-info/WHEEL
traceai_guardrails-0.1.4.dist-info/RECORD
