Metadata-Version: 2.3
Name: traceAI-guardrails
Version: 0.1.4
Summary: OpenTelemetry instrumentation for Guardrails
Author: Future AGI
Author-email: no-reply@futureagi.com
Requires-Python: >3.9,<3.13
Classifier: Programming Language :: Python :: 3
Classifier: Programming Language :: Python :: 3.10
Classifier: Programming Language :: Python :: 3.11
Classifier: Programming Language :: Python :: 3.12
Requires-Dist: fi-instrumentation-otel (>=0.1.11)
Requires-Dist: guardrails-ai (>=0.4.5,<0.5.1)
Requires-Dist: packaging
